yamlconf/__init__.py
yamlconf/about.py
yamlconf/errors.py
yamlconf/import_module.py
yamlconf/import_path.py
yamlconf/load.py
yamlconf/merge.py
yamlconf/propagate_defaults.py
yamlconf/tests/__init__.py
yamlconf/tests/test_import_path.py
yamlconf/tests/test_load.py
yamlconf/tests/test_merge.py
yamlconf/tests/test_propagate_defaults.py
yamlconf/tests/util/__init__.py
yamlconf/tests/util/submodule.py
yamlconf/tests/util/value.py
yamlconf_wmf-0.2.10.dist-info/LICENSE
yamlconf_wmf-0.2.10.dist-info/METADATA
yamlconf_wmf-0.2.10.dist-info/WHEEL
yamlconf_wmf-0.2.10.dist-info/top_level.txt
yamlconf_wmf-0.2.10.dist-info/RECORD
