Metadata-Version: 2.1
Name: yamlconf-wmf
Version: 0.2.10
Summary: Yaml-based configuration file reader. This is a fork of the original yamlfconf package. This fork is maintained by WMF Machine Learning Team
Home-page: https://github.com/wikimedia/yamlconf
Author: Aaron Halfaker
Author-email: aaron.halfaker@gmail.com
License: MIT
Classifier: Development Status :: 4 - Beta
Classifier: Programming Language :: Python
Classifier: Programming Language :: Python :: 3
Classifier: Environment :: Other Environment
Classifier: Intended Audience :: Developers
Classifier: License :: OSI Approved :: MIT License
Classifier: Operating System :: OS Independent
Classifier: Topic :: Software Development :: Libraries :: Python Modules
License-File: LICENSE
Requires-Dist: pyyaml ==6.0.1
